LICENSE
MANIFEST.in
README.md
package.json
setup.py
thinks_dash_input/ThinksDashInputNumber.py
thinks_dash_input/__init__.py
thinks_dash_input/_imports_.py
thinks_dash_input/metadata.json
thinks_dash_input/package-info.json
thinks_dash_input/thinks_dash_input.min.js
thinks_dash_input/thinks_dash_input.min.js.map
thinks_dash_input.egg-info/PKG-INFO
thinks_dash_input.egg-info/SOURCES.txt
thinks_dash_input.egg-info/dependency_links.txt
thinks_dash_input.egg-info/top_level.txt