Metadata-Version: 2.1
Name: thinks-dash-input
Version: 0.0.3
Summary: Dash Input Component
Author: thinkup-sol <s_matsumoto@thinkup-sol.co.jp>
License: MIT
Classifier: Framework :: Dash
License-File: LICENSE
